[{"client_msg_id":"2ddf7705-91b9-4fc5-b6cb-8d3d7d7abe69","type":"message","text":"昔つくったfewコマンドはかなり好き","user":"U03C4RC8X","ts":"1586235208.211800","team":"T03C4RC8V","user_team":"T03C4RC8V","source_team":"T03C4RC8V","blocks":[{"block_id":"oyjM","elements":[{"elements":[{"text":"昔つくったfewコマンドはかなり好き","type":"text"}],"type":"rich_text_section"}],"type":"rich_text"}]},{"client_msg_id":"d9033d4a-5603-4f63-b558-0c6d74e962a0","type":"message","text":"lessの次","user":"U03C4RC8X","ts":"1586235214.212000","team":"T03C4RC8V","user_team":"T03C4RC8V","source_team":"T03C4RC8V","blocks":[{"block_id":"i0yLr","elements":[{"elements":[{"text":"lessの次","type":"text"}],"type":"rich_text_section"}],"type":"rich_text"}],"reactions":[{"name":"fukaikousatsu","users":["UL6CFN8NR","U7B4ZD49X"],"count":2}]}]
